manim_qr_codes/docbuild/__init__.py
manim_qr_codes/docbuild/manta_directive.py
manim_qr_codes/logger.py
manim_qr_codes/qr.py
manim_qr_codes-0.1.0.dist-info/METADATA
manim_qr_codes-0.1.0.dist-info/WHEEL
manim_qr_codes-0.1.0.dist-info/RECORD
