Metadata-Version: 2.3
Name: manim-qr-codes
Version: 0.1.0
Summary: A Manim plugin for creating QR-codes.
License: MIT
Author: Alexander Nasuta
Author-email: alexander.nasuta@wzl-iqs.rwth-aachen.de
Requires-Python: >=3.11,<4.0
Classifier: License :: OSI Approved :: MIT License
Classifier: Programming Language :: Python :: 3
Classifier: Programming Language :: Python :: 3.11
Classifier: Programming Language :: Python :: 3.12
Classifier: Programming Language :: Python :: 3.13
Requires-Dist: manim (>=0.19.0,<0.20.0)
Requires-Dist: manim-nerdfont-icons (>=1.0.0,<2.0.0)
Requires-Dist: segno (>=1.6.1,<2.0.0)
